_jieba_fast_functions_py3.cpython-312-x86_64-linux-gnu.so
jieba_pyfast/__init__.py
jieba_pyfast/_compat.py
jieba_pyfast/dict.txt
jieba_pyfast/jieba_fast_functions_py3.py
jieba_pyfast/finalseg/__init__.py
jieba_pyfast/finalseg/jieba_fast_functions_py3.py
jieba_pyfast/finalseg/prob_emit.p
jieba_pyfast/finalseg/prob_emit.py
jieba_pyfast/finalseg/prob_start.p
jieba_pyfast/finalseg/prob_start.py
jieba_pyfast/finalseg/prob_trans.p
jieba_pyfast/finalseg/prob_trans.py
jieba_pyfast/posseg/__init__.py
jieba_pyfast/posseg/char_state_tab.p
jieba_pyfast/posseg/char_state_tab.py
jieba_pyfast/posseg/prob_emit.p
jieba_pyfast/posseg/prob_emit.py
jieba_pyfast/posseg/prob_start.p
jieba_pyfast/posseg/prob_start.py
jieba_pyfast/posseg/prob_trans.p
jieba_pyfast/posseg/prob_trans.py
jieba_pyfast/posseg/viterbi.py
jieba_pyfast/source/jieba_fast_functions_py3.py
jieba_pyfast/source/jieba_fast_functions_wrap_py3.i
jieba_pyfast/source/jieba_fast_functions_wrap_py3_wrap.c
jieba_pyfast-3.13.3.dist-info/LICENSE
jieba_pyfast-3.13.3.dist-info/METADATA
jieba_pyfast-3.13.3.dist-info/WHEEL
jieba_pyfast-3.13.3.dist-info/RECORD
