Metadata-Version: 2.3
Name: jieba_pyfast
Version: 3.13.3
Summary: Tokenize Chinese characters
License: MIT
Author: snapADDY GmbH
Author-email: info@snapaddy.com
Requires-Python: >=3.11,<4.0
Classifier: License :: OSI Approved :: MIT License
Classifier: Programming Language :: Python :: 3
Classifier: Programming Language :: Python :: 3.11
Classifier: Programming Language :: Python :: 3.12
Classifier: Programming Language :: Python :: 3.13
